cast/__init__.py
cast/__version__.py
cast/cli.py
cast/cliprint.py
cast/conform.py
cast/dirdiff.py
cast/exceptions.py
cast/logconf.py
cast/template/__init__.py
cast/template/core.py
cast/template/path.py
cast/template/registry.py
fscast-0.0.2.dist-info/DESCRIPTION.rst
fscast-0.0.2.dist-info/METADATA
fscast-0.0.2.dist-info/RECORD
fscast-0.0.2.dist-info/WHEEL
fscast-0.0.2.dist-info/entry_points.txt
fscast-0.0.2.dist-info/metadata.json
fscast-0.0.2.dist-info/top_level.txt
