Metadata-Version: 2.0
Name: fscast
Version: 0.0.2
Summary: FIle System Templates
Home-page: https://github.com/taesko/cast
Author: Antonio Todorov
Author-email: taeskow@gmail.com
License: MIT
Platform: UNKNOWN
Classifier: Development Status :: 3 - Alpha
Classifier: Operating System :: POSIX :: Linux
Classifier: License :: OSI Approved :: MIT License
Classifier: Programming Language :: Python :: 3.6
Classifier: Programming Language :: Python :: Implementation :: CPython
Requires-Python: >=3.6
Requires-Dist: click
